{"msg":"success!","code":"000000","data":[{"project_classify":[{"value":"投资"}],"region_scale_ext":"100.15公顷","sys_dictionary_payment_method":[],"prequalification_notice_date":"2017-09-20","audit_status":"WAIT_AUDIT","project_name":"沁县松村至迎春公路（太焦高铁连接线）PPP项目","build_phase_ext":null,"special_attribute":null,"province":[{"name":"山西省"}],"cooperation_phase_ext":null,"project_id":21761,"attach_file":"\"[]\"","prequalification_bid_notice_date":null,"id":21761,"region_scale":"1.00","bid_condition":"<p>2、社会资本资格条件<\/p><p>2.1应符合《中华人民共和国政府采购法》第二十二条第一款的第（一）至（六）项规定。<\/p><p>2.2依法注册且合法存续的企业法人，有效的营业执照、税务登记证书、组织机构代码证，或新版企业营业执照副本（三合一证）；<\/p><p>2.3资质要求：具备国家建设行政管理部门颁发的公路工程施工总承包贰级及以上资质或市政公用工程施工总承包壹级及以上资质，具备有效的安全生产许可证。<\/p><p>2.4业绩经验要求：近5年内完成过不少于3个公路或市政公用工程项目（累计合同金额不低于1亿元人民币），须提供相关证明资料(原件查验、复印件留存)，须同时提供中标通知书、施工合同、竣工验收证明，以竣工验收时间为准。<\/p><p>2.5财务要求：<\/p><p>（1）申请人注册资本金不低于人民币3亿元整，以营业执照为准；<\/p><p>（2）申请人资产负债率不高于85%；<\/p><p>（3）申请人提供具有相应资质的会计师事务所出具的2014年-2016年度审计报告。近三年财务状况均为盈利，经审计的年均企业总资产不低于20亿元整，年均净资产不低于人民币3亿元整。<\/p><p>2.6投融资能力：<\/p><p>申请人的银行授信额度不低于8亿元，以银行（或金融机构）对该申请人出具的授信额度合同或贷款意向书为准。<\/p><p>2.7申请人近三年内无不良经营行为，没有发生过重大生产安全和质量事故或重大投诉事件等违法行为，申请人均应提供当地检察机关出具的无犯罪证明记录；<\/p><p>2.8本项目接受联合体投标。以联合体申请资格预审的，联合体成员均需提供2.2及2.7所要求文件，其余各项只要联合体成员之一满足即可；联合体应提交联合体协议书并注明牵头人及各方拟承担的工作和责任，并承诺一旦成为联合体将向采购人承担连带责任；联合体各方不得再单独参加或者与其他申请人另外组成联合体参加同一合同项下的政府采购活动；联合体牵头方法定代表人或其授权的委托代理人负责签署本次资格预审申请相关资料，其他联合体各方对此予以认可。通过资格预审的联合体，不得再变更其组织形式及成员构成。<\/p>","buyer_category":null,"area":"华北地区","prequalification_bid_notice":null,"town":[{"name":"沁县"}],"create_time":"2017-09-20 14:57:29","project_survey":"<p>1、项目概况与招标范围<\/p><p>1.1建设地点：<\/p><p>项目位于长治市武乡县和沁县境内，东起武乡县西陈村北太焦高铁武乡西站，终点位于迎春村东北，与省道322相接，是实现高速铁路与县城之间快速连接的交通要道。<\/p><p>1.2建设内容：<\/p><p>本项目拟建项目路线全线长17.10公里,全部为新建工程，全线采用一级公路标准建设，设计速度80公里/小时，路基宽度30.0米，桥涵荷载等级为公路Ⅰ级标准。连接线工程长度1.477公里（二级公里标准，路基宽度12米）。主要工程规模如下：<\/p><p>推荐方案计价土方1709.318千立方米，计价石方468.005千立方米，排水防护工程1853.59百立方米，特殊路基处理3.25公里，路面工程420.686千平方米；大桥2座，长612米，中桥5座，长158米，涵洞66道，互通立交2座，通道5座，天桥2座，平面交叉12处，沿线交通设施18.577公里，拆迁房屋5900平方米，全线需征地100.15公顷。本项目施工工期拟定为2017年11月至2019年11月，于2019年末建成通车。<\/p><p>1.3前期工作：<\/p><p>本项目已纳入沁县城市总体规划，完成可行性研究报告的评审，并获得环保、文物保护的初评意见和国土资源局的批复。<\/p><p>1.4运作模式：<\/p><p>本项目运作模式为建设-运营-移交（BOT）。项目实施机构通过招标程序选定社会资本与政府指定的政府方出资代表合资组建项目公司，并与项目公司签订《PPP项目合同》，授权项目公司在项目期限内负责本项目的投资、建设、运营、维护工作。项目合作期满后，项目公司将项目设施完好、完整、无偿的移交给沁县人民政府或其指定机构。<\/p><p>项目运营维护范围包括：项目红线范围内的道路、管网（排水）、绿地、照明等公共基础设施的管养与维护。<\/p><p>1.5回报机制：<\/p><p>项目公司收益分为可用性服务费与运维绩效考核服务费，项目公司收益中的运维绩效考核服务费与对项目公司的绩效考核挂钩，即运营期内县政府依据《PPP项目合同》约定的政府付费计算方式及绩效权重，支付可行性服务费，并结合项目公司考核结果支付运维绩效服务费，以覆盖项目的建设、运营维护成本和合理利润。<\/p><p>1.6合作期限：<\/p><p>项目合作期为22年，其中建设期2年，运营维护期20年。<\/p><p>1.7投融资结构：<\/p><p>总投资概算为65436.62万元。项目公司的注册资本金按总投资的20.63%计算，即人民币13500.00万元。其中沁县财苑国资有限公司代表政府出资人民币1350.00万元，股权占比10%；社会资本方出资12150.00万元，股权占比90%。总投资的79.37%即52349.29万元，由中选社会资本方负责融资。<\/p>","version":6,"begin_bid_time":"2017-11-23","investment_scale":"6.5437亿元","winning_category":null,"operation_pattern_ext":null,"pre_bid_notice_end_date":null,"first_industry":[{"value":"交通运输"}],"operate_phase":"240","create_user":10,"open_bid_notice":"<p>沁县交通运输局沁县松村至迎春公路（太焦高铁连接线）PPP项目选择社会资本招标公告<\/p><p>招标编号：CGCI-ZL-2017059-1<\/p><p>沁县交通运输局沁县松村至迎春公路（太焦高铁连接线）PPP项目选择社会资本招标公告<\/p><p>沁县松村至迎春公路（太焦高铁连接线）PPP项目由沁县人民政府批准建设（可研报告批复编号：沁发改审发（2017）137号），并授权沁县交通运输局为项目实施机构，负责本项目社会资本的招标采购工作。中仪国际招标有限公司受沁县交通运输局委托，按照《中华人民共和国政府采购法》《中华人民共和国政府采购法实施条例》及《政府和社会资本合作项目政府采购管理办法》等有关法规，采用公开招标方式择优选择社会资本，邀请本项目已通过资格预审的潜在社会资本参与公开招标。<\/p><p>项目名称：沁县松村至迎春公路（太焦高铁连接线）PPP项目<\/p><p>项目编号：CGCI-ZL-2017059<\/p><p>项目授权主体：沁县人民政府<\/p><p>项目实施机构：沁县交通运输局<\/p><p>采购代理机构：中仪国际招标有限公司<\/p><p>政府方出资代表：沁县财苑国资有限公司<\/p><p>一、项目概况与招标范围<\/p><p>1.1建设地点：<\/p><p>项目位于长治市武乡县和沁县境内，东起武乡县西陈村北太焦高铁武乡西站，终点位于迎春村东北，与省道322相接，是实现高速铁路与县城之间快速连接的交通要道。<\/p><p>1.2建设内容：<\/p><p>本项目拟建项目路线全线长17.10公里,全部为新建工程，全线采用一级公路标准建设，设计速度80公里/小时，路基宽度30.0米，桥涵荷载等级为公路Ⅰ级标准。连接线工程长度1.477公里（二级公里标准，路基宽度12米）。主要工程规模如下：<\/p><p>推荐方案计价土方1709.318千立方米，计价石方468.005千立方米，排水防护工程1853.59百立方米，特殊路基处理3.25公里，路面工程420.686千平方米；大桥2座，长612米，中桥5座，长158米，涵洞66道，互通立交2座，通道5座，天桥2座，平面交叉12处，沿线交通设施18.577公里，拆迁房屋5900平方米，全线需征地100.15公顷。本项目施工工期拟定为2017年11月至2019年11月，于2019年末建成通车。<\/p><p>1.3前期工作：<\/p><p>本项目已纳入沁县城市总体规划，完成可行性研究报告的评审，并获得环保、文物保护的初评意见和国土资源局的批复。已通过项目的《财政承受能力评估报告》、《物有所值评估报告》专家评审，获得了《关于沁县松村至迎春公路（太焦高铁连接线）PPP项目实施方案的批复》（沁政函〔2017〕55号），以PPP模式运作的前期条件已具备。<\/p><p>1.4运作模式：<\/p><p>本项目运作模式为建设-运营-移交（BOT）。项目实施机构通过招标程序选定社会资本与政府指定的政府方出资代表合资组建项目公司，并与项目公司签订《PPP项目合同》，授权项目公司在项目期限内负责本项目的投资、建设、运营、维护工作。项目合作期满后，项目公司将项目设施完好、完整、无偿的移交给沁县人民政府或其指定机构。<\/p><p>项目运营维护范围包括：项目红线范围内的道路、管网（排水）、绿地、照明等公共基础设施的管养与维护。<\/p><p>1.5回报机制：<\/p><p>项目公司收益分为可用性服务费与运维绩效考核服务费，项目公司收益中的运维绩效服务费与对项目公司的绩效考核挂钩，即运营期内县政府依据《PPP项目合同》约定的政府付费计算方式及绩效权重，支付可行性服务费，并结合项目公司考核结果支付运维绩效服务费，以覆盖项目的建设、运营维护成本和合理利润。<\/p><p>1.6合作期限：<\/p><p>项目合作期为22年，其中建设期2年，运营维护期20年。<\/p><p>1.7投融资结构：<\/p><p>可研批复估算总投资为65436.62万元。项目公司的注册资本金按总投资的20.63%计算，即人民币13500.00万元。其中沁县财苑国资有限公司代表政府出资人民币1350.00万元，股权占比10%；社会资本方出资12150.00万元，股权占比90%。总投资的79.37%即51936.62万元，由中选社会资本方负责融资。<\/p><p>1.8绩效目标要求：<\/p><p>（1）工期目标：二年。<\/p><p>（2）交、竣工验收的工程质量目标：交、竣工验收的质量评定均在合格及以上等级，且质量综合评分90分；<\/p><p>（3）运营养护目标：<\/p><p>①根据《公路技术状况评定标准》（JTGH20-2007）的有关规定和评价标准，应达到优良水平，公路技术状况指数MQI80，路面使用性能指数PQI80，路基技术状况指数SCI75，桥隧构造物技术状况指数BCI75，沿线设施技术状况指数TCI75；<\/p><p>②养护工程质量目标：合格率达到100%，优良率达到90%。<\/p><p>③树木、花草的成活率80％，保存率75％。<\/p><p>（4）服务质量目标：项目的服务水平应不低于经批准的工程可行性研究报告中相关计算值。<\/p><p>（5）安全目标：杜绝一般及以上安全生产责任事故。<\/p><p>二、政府采购政策要求<\/p><p>本项目执行《中华人民共和国政府采购法》、《中华人民共和国政府采购法实施条例》、《政府和社会资本合作模式操作指南（试行）》（财金〔2014〕113号）、《政府和社会资本合作项目政府采购管理办法》（财金〔2014〕215号）等法律、法规、规章、规范性文件规定的各项政府采购政策。<\/p><p>本项目优先采购本国货物和服务，须进行的技术引进和转让需符合国家政策和有利于国内行业的发展。项目中涉及到的设备、材料属于政府采购节能产品、环境标志产品的，应当符合相关规定。<\/p><p>三、投标人资格要求<\/p><p>参加本次公开招标的社会资本应为已通过本项目资格预审的社会资本，本项目不允许未参加资格预审的社会资本参与公开招标。<\/p><p>四、招标文件的获取<\/p><p>凡符合资格条件要求并有意参加竞争的申请人请携带单位介绍信、《法定代表人授权书》、授权代理人身份证原件和复印件，于2017年11月23日起至2017年11月29日每日上午9：00-12：00，下午14:00-17:00到中国通用招标网上登记并购买招标文件，招标文件每套售价人民币1000元，售后不退，逾期不予办理。<\/p><p>五、投标文件的提交<\/p><p>5.1投标文件提交时间为2017年12月14日13:30-14：00时，截止时间为14:00整（北京时间）；<\/p><p>5.2投标文件提交地点为：山西省政协宾馆二层会议室（V3）<\/p><p>5.3逾期送达的或者未送达指定地点的投标文件，采购人不予受理；<\/p><p>5.4投标申请人的法定代表人或其授权委托人到场参加开标，否则其投标无效。<\/p><p>六、其他说明<\/p><p>6.1发布公告的媒介<\/p><p>本次招标公告同时在《____》、《中国政府采购网》、《山西省政府采购网》和《中国通用招标网》网上发布。<\/p><p>6.2采购人可能对本招标公告进行修改，若有修改，采购人将对报名的申请人发布更正公告。经项目授权主体同意，采购人有权单方终止本项目采购活动并无需向报名申请人承担任何责任。采购人具有本公告的最终解释权。<\/p><p>6.3采购人将向中标的申请人发出中标通知书。未收到中标通知书的申请人则不再另行通知，采购人和采购代理机构对中标结果不承担解释的责任。<\/p><p>七、联系方式<\/p><p>采购人：沁县交通运输局<\/p><p>联系地址：沁县友谊街一号<\/p><p>联系人：王秀锦<\/p><p>电话：0355－7023302<\/p><p>采购代理机构：中仪国际招标有限公司<\/p><p>地址：北京市丰台区西三环中路90号通用技术大厦1502B<\/p><p>联系人：李朝晖李永科<\/p><p>电话：010-63348240/63348921<\/p><p>邮箱：lizhaohui@itc.genertec.com.cn<\/p><p>liyongke@gtc.genertec.com.cn<\/p><p>中仪国际招标有限公司<\/p><p>2017年11月23日<\/p>","city":[{"name":"长治市"}],"pre_bid_notice_begin_date":null,"cooperation_phase":"22年","remark":null,"project_types":null,"audit_time":null,"collection_bid":"全投资税后财务内部收益率（%）：6.48。\n运维绩效费用报价：①日常维护 0.39 元/平米*月；②中修（每五年） 13.86 元/平米*次；③大修（每十年） 27.72 元/平米*次。","agency_company":{"update_time":"2017-04-19 00:00:00","update_user":1,"create_time":"2017-04-19 00:00:00","name":"中仪国际招标有限公司","id":4398,"create_user":1,"version":0},"update_time":"2017-12-20 10:35:22","company_single":[],"update_user":9,"notice_url":"\"[{\"name\":\"\\u8d44\\u683c\\u9884\\u5ba1\\u6587\\u4ef6\",\"url\":\"http:\\/\\/www.china-tender.com.cn\\/u\\/cms\\/www\\/201710\\/2308583649e0.docx\"},{\"name\":\"\\u62db\\u6807\\u6587\\u4ef6\",\"url\":\"http:\\/\\/www.ccgp.gov.cn\\/cggg\\/dfgg\\/zbgg\\/201712\\/t20171219_9359508.htm\"}]\"","payment_method_detail":"<p>项目公司收益分为可用性服务费与运维绩效考核服务费，项目公司收益中的运维绩效考核服务费与对项目公司的绩效考核挂钩，即运营期内县政府依据《PPP项目合同》约定的政府付费计算方式及绩效权重，支付可行性服务费，并结合项目公司考核结果支付运维绩效服务费，以覆盖项目的建设、运营维护成本和合理利润。\t\t\t\t<\/p>","submit_audit_time":"2017-12-20 10:35:22","win_bid_time":"2017-12-19","agency":"4398","view_company_project":[{"area":"华北地区","abbreviate":"山西二建集团有限公司","is_listed":"上市公司","create_time":"2017-09-27 11:11:46","nature":{"value":"地方国有控股企业"},"remark":null,"type":"INVESTMENT","version":1,"update_time":"2017-09-27 11:49:44","update_user":2,"province":{"name":"北京"},"parent_id":null,"name":"山西二建集团有限公司","pivot":{"company_id":5372,"project_id":21761},"id":5372,"create_user":9},{"area":"华北地区","abbreviate":"山西晋财惠晋资本管理有限公司","is_listed":"上市公司","create_time":"2017-10-31 11:13:35","nature":{"value":"民营企业"},"remark":null,"type":"INVESTMENT","version":1,"update_time":"2017-11-01 17:48:39","update_user":2,"province":{"name":"北京"},"parent_id":null,"name":"山西晋财惠晋资本管理有限公司","pivot":{"company_id":5608,"project_id":21761},"id":5608,"create_user":9}],"serial_num":"201709200031","is_allow_union":1,"operate_phase_ext":null,"collection_bidder":"山西二建集团有限公司与山西晋财惠晋资本管理有限公司联合体","sys_dictionary_operation_pattern":[{"pivot":{"project_id":21761,"operation_pattern_id":16},"id":16,"value":"BOT"}],"project_schedule":"BID","procurement_mode":[{"value":"公开招标"}],"second_industry":[{"value":"公路桥隧"}],"investment_scale_ext":null,"prequalification_notice":"<p>沁县松村至迎春公路（太焦高铁连接线）PPP项目由沁县人民政府批准建设（可研报告批复编号：沁发改审发（2017）137号），并授权沁县交通运输局为项目实施机构，负责本项目社会资本的招标采购工作。中仪国际招标有限公司受沁县交通运输局委托，按照《中华人民共和国政府采购法》《中华人民共和国政府采购法实施条例》及《政府和社会资本合作项目政府采购管理办法》等有关法规组织实施该项目的社会资本采购工作。特邀请符合条件的社会资本（下称“申请人”）参与资格预审，现将资格预审有关事宜公告如下。<\/p><p>项目名称：沁县松村至迎春公路（太焦高铁连接线）PPP项目<\/p><p>项目编号：CGCI-ZL-2017059<\/p><p>项目授权主体：沁县人民政府<\/p><p>项目实施机构：沁县交通运输局<\/p><p>采购代理机构：中仪国际招标有限公司<\/p><p>政府方出资代表：沁县财苑国资有限公司<\/p><p>1、项目概况与招标范围<\/p><p>1.1建设地点：<\/p><p>项目位于长治市武乡县和沁县境内，东起武乡县西陈村北太焦高铁武乡西站，终点位于迎春村东北，与省道322相接，是实现高速铁路与县城之间快速连接的交通要道。<\/p><p>1.2建设内容：<\/p><p>本项目拟建项目路线全线长17.10公里,全部为新建工程，全线采用一级公路标准建设，设计速度80公里/小时，路基宽度30.0米，桥涵荷载等级为公路Ⅰ级标准。连接线工程长度1.477公里（二级公里标准，路基宽度12米）。主要工程规模如下：<\/p><p>推荐方案计价土方1709.318千立方米，计价石方468.005千立方米，排水防护工程1853.59百立方米，特殊路基处理3.25公里，路面工程420.686千平方米；大桥2座，长612米，中桥5座，长158米，涵洞66道，互通立交2座，通道5座，天桥2座，平面交叉12处，沿线交通设施18.577公里，拆迁房屋5900平方米，全线需征地100.15公顷。本项目施工工期拟定为2017年11月至2019年11月，于2019年末建成通车。<\/p><p>1.3前期工作：<\/p><p>本项目已纳入沁县城市总体规划，完成可行性研究报告的评审，并获得环保、文物保护的初评意见和国土资源局的批复。<\/p><p>1.4运作模式：<\/p><p>本项目运作模式为建设-运营-移交（BOT）。项目实施机构通过招标程序选定社会资本与政府指定的政府方出资代表合资组建项目公司，并与项目公司签订《PPP项目合同》，授权项目公司在项目期限内负责本项目的投资、建设、运营、维护工作。项目合作期满后，项目公司将项目设施完好、完整、无偿的移交给沁县人民政府或其指定机构。<\/p><p>项目运营维护范围包括：项目红线范围内的道路、管网（排水）、绿地、照明等公共基础设施的管养与维护。<\/p><p>1.5回报机制：<\/p><p>项目公司收益分为可用性服务费与运维绩效考核服务费，项目公司收益中的运维绩效考核服务费与对项目公司的绩效考核挂钩，即运营期内县政府依据《PPP项目合同》约定的政府付费计算方式及绩效权重，支付可行性服务费，并结合项目公司考核结果支付运维绩效服务费，以覆盖项目的建设、运营维护成本和合理利润。<\/p><p>1.6合作期限：<\/p><p>项目合作期为22年，其中建设期2年，运营维护期20年。<\/p><p>1.7投融资结构：<\/p><p>总投资概算为65436.62万元。项目公司的注册资本金按总投资的20.63%计算，即人民币13500.00万元。其中沁县财苑国资有限公司代表政府出资人民币1350.00万元，股权占比10%；社会资本方出资12150.00万元，股权占比90%。总投资的79.37%即52349.29万元，由中选社会资本方负责融资。<\/p><p>2、社会资本资格条件<\/p><p>2.1应符合《中华人民共和国政府采购法》第二十二条第一款的第（一）至（六）项规定。<\/p><p>2.2依法注册且合法存续的企业法人，有效的营业执照、税务登记证书、组织机构代码证，或新版企业营业执照副本（三合一证）；<\/p><p>2.3资质要求：具备国家建设行政管理部门颁发的公路工程施工总承包贰级及以上资质或市政公用工程施工总承包壹级及以上资质，具备有效的安全生产许可证。<\/p><p>2.4业绩经验要求：近5年内完成过不少于3个公路或市政公用工程项目（累计合同金额不低于1亿元人民币），须提供相关证明资料(原件查验、复印件留存)，须同时提供中标通知书、施工合同、竣工验收证明，以竣工验收时间为准。<\/p><p>2.5财务要求：<\/p><p>（1）申请人注册资本金不低于人民币3亿元整，以营业执照为准；<\/p><p>（2）申请人资产负债率不高于85%；<\/p><p>（3）申请人提供具有相应资质的会计师事务所出具的2014年-2016年度审计报告。近三年财务状况均为盈利，经审计的年均企业总资产不低于20亿元整，年均净资产不低于人民币3亿元整。<\/p><p>2.6投融资能力：<\/p><p>申请人的银行授信额度不低于8亿元，以银行（或金融机构）对该申请人出具的授信额度合同或贷款意向书为准。<\/p><p>2.7申请人近三年内无不良经营行为，没有发生过重大生产安全和质量事故或重大投诉事件等违法行为，申请人均应提供当地检察机关出具的无犯罪证明记录；<\/p><p>2.8本项目接受联合体投标。以联合体申请资格预审的，联合体成员均需提供2.2及2.7所要求文件，其余各项只要联合体成员之一满足即可；联合体应提交联合体协议书并注明牵头人及各方拟承担的工作和责任，并承诺一旦成为联合体将向采购人承担连带责任；联合体各方不得再单独参加或者与其他申请人另外组成联合体参加同一合同项下的政府采购活动；联合体牵头方法定代表人或其授权的委托代理人负责签署本次资格预审申请相关资料，其他联合体各方对此予以认可。通过资格预审的联合体，不得再变更其组织形式及成员构成。<\/p><p>3、资格预审方法<\/p><p>资格预审采用合格制，具体审查办法详见资格预审文件。<\/p><p>4、资格预审文件的获取<\/p><p>4.1凡符合资格条件要求并有意参加竞争的申请人请于2017年10月21日起至2017年10月27日每日上午9：00-12：00，下午14:00-17:00到中国通用招标网（http://www.china-tender.com.cn/）注册并购买资格预审文件，资格预审文件每套售价人民币1000元，售后不退，逾期不予办理。<\/p><p>5、资格预审申请文件的提交<\/p><p>5.1资格预审申请文件提交时间为2017年11月11日8:30-9：00时，截止时间为9:00整（北京时间）；<\/p><p>5.2资格预审申请文件提交地点为：山西省政协宾馆二层会议室（V3）<\/p><p>5.3逾期送达的或者未送达指定地点的资格预审申请文件，采购人不予受理；<\/p><p>5.4资格预审申请人的法定代表人或其授权委托人到场参加资格审查，否则其资格审查无效。<\/p><p>6、其他说明<\/p><p>6.1发布公告的媒介<\/p><p>本次招标公告同时在《中国采购与招标网》、《中国政府采购网》、《山西省政府采购网》和《中国通用招标网》网上发布。<\/p><p>6.2采购人可能对本资格预审公告进行修改，若有修改，采购人将对报名的申请人发布更正公告。经项目授权主体同意，采购人有权单方终止本项目采购活动并无需向报名申请人承担任何责任。采购人具有本公告的最终解释权。<\/p><p>6.3采购人将向通过资格预审的申请人发出投标邀请书。未收到投标邀请书的申请人则未能入选成为本项目的申请人，采购人和采购代理机构对此不承担解释的责任。<\/p><p>7、联系方式<\/p><p>采购人：沁县交通运输局<\/p><p>联系地址：沁县友谊街一号<\/p><p>联系人：王秀锦<\/p><p>电话：0355－7023302<\/p><p>采购代理机构：中仪国际招标有限公司<\/p><p>地址：北京市丰台区西三环中路90号通用技术大厦1502室<\/p><p>联系人：李朝晖李永科<\/p><p>电话：010-63348240/63348921<\/p><p>邮箱：lizhaohui@itc.genertec.com.cn<\/p><p>liyongke@gtc.genertec.com.cn<\/p>","bid":[{"company_type":"UNION","create_time":"2017-12-20 10:35:22","sys_dictionary":{"id":43,"value":"%"},"bid_type":{"id":127,"value":"全投资收益率"},"type":127,"version":0,"cal_value":null,"unit":43,"update_time":"2017-12-20 10:35:22","update_user":9,"project_id":21761,"second_type":null,"name":"全投资税后财务内部收益率","company":6171,"id":38549,"create_user":9,"value":"6.48"},{"company_type":"UNION","create_time":"2017-12-20 10:35:22","sys_dictionary":{"id":174,"value":"元/平方米·月"},"bid_type":{"id":126,"value":"运营成本单价"},"type":126,"version":0,"cal_value":null,"unit":174,"update_time":"2017-12-20 10:35:22","update_user":9,"project_id":21761,"second_type":null,"name":"运维绩效费用报价：日常维护","company":6171,"id":38550,"create_user":9,"value":"0.39"}],"build_phase":"24","bid_company_id":[{"name":"沁县交通运输局"}]}]}