{"msg":"success!","code":"000000","data":[{"project_classify":[{"value":"投资"}],"region_scale_ext":null,"sys_dictionary_payment_method":[{"pivot":{"payment_method_id":31,"project_id":21771},"id":31,"value":"可行性缺口补贴"}],"prequalification_notice_date":"2017-09-20","audit_status":"WAIT_AUDIT","project_name":"沙湾县生活垃圾综合处理厂PPP项目","build_phase_ext":null,"special_attribute":null,"province":[{"name":"新疆维吾尔自治区"}],"cooperation_phase_ext":null,"project_id":21771,"attach_file":"\"[]\"","prequalification_bid_notice_date":null,"id":21771,"region_scale":null,"bid_condition":"<p>六、申请人资格条件<\/p><p>1.申请人需满足《中华人民共和国政府采购法》第二十二条的相关规定：<\/p><p>1)投标人必须是在中华人民共和国境内（不含港、澳、台企业）依法注册的企业法人，具有独立承担民事责任的能力，且具有有效的营业执照、税务登记证书、组织机构代码证；申请人注册资金不低于5000万人民币（联合体投标的，至少一方满足对注册资本金的要求）；<\/p><p>2)具有良好的商业信誉和健全的财务会计制度；<\/p><p>3)有依法缴纳税收和社会保障资金的良好记录；<\/p><p>4)参加政府采购活动前三年内，在经营活动中没有重大违法的声明；<\/p><p>5)法律、行政法规规定的其他条件。<\/p><p>2.申请人须无行贿犯罪记录；<\/p><p>3.申请人应有良好的财务状况，须提供2016年度的财务报告或审计报告；<\/p><p>4.申请人至少在2016年7月1日至2017年7月1日至少具有一个合同额不低于500万元的环保工程项目业绩；<\/p><p>5.供应商在信用中国网站（www.creditchina.gov.cn）和《中国政府采购网》（www.ccgp.gov.cn）上被列入失信被执行人、重大税收违法案件当事人名单、政府采购严重违法失信行为记录名单的，不得参加投标；<\/p><p>6.本项目接受联合体申请。但联合体成员单位不超过两家，联合体各方除上述第1条、第2条和第5条均需满足外，第3条、第4条需至少有联合体成员中一方满足。<\/p>","buyer_category":null,"area":"西北地区","prequalification_bid_notice":null,"town":[{"name":"沙湾县"}],"create_time":"2017-09-21 10:10:34","project_survey":"<p>一、采购项目编号：GXTC-1751112<\/p><p>二、项目名称：沙湾县生活垃圾综合处理厂PPP项目<\/p><p>三、本项目暂定总投资：人民币13506.68万元。<\/p><p>四、项目概况<\/p><p>随着生活垃圾对环境的污染和公共卫生安全的危害日益显现，为了加强生活垃圾管理，维护城市面貌和环境卫生，实现生活垃圾的无害化、减量化和资源化处置，因此沙湾县决定启动建设生活垃圾综合处理厂项目。根据项目规划要求，本项目拟处理沙湾县城与周边乡镇产生的生活垃圾。<\/p><p>沙湾县生活垃圾综合处理厂项目的设计处理总规模为300吨/日。生活垃圾综合处理厂初步拟建于沙湾县城北侧9公里处的规划红线范围内。<\/p><p>本项目拟采用热解还原综合处理技术工艺。项目的主要建设内容包括：热解还原系统、逆流烘干系统、复合烟气净化系统、燃气发电系统、污水处理系统、实时监控系统及相关配套设施。<\/p><p>五、采购需求<\/p><p>本项目通过公开招标的方式选择社会投资人，由中标的社会投资人与政府指定的出资方代表沙湾县汇福融祥投资有限公司共同在项目所在地组建项目公司，项目资本金比例为20%（即2701.34万元），其中政府方出资代表和社会资本方占项目公司股权比例分别为10%、90%（政府出资270万元，合格的社会资本自筹2431.34万元），债务性融资为80%（即10805.34万元），融资期限20年。本项目采用政府和社会资本合作（PPP）模式，具体运作方式为建设运营移交（BOT），回报机制为可行性缺口补助。项目公司获得政府授予的特许经营权，特许经营期为30年（含建设期1年，运营维护期29年）。项目公司负责项目的投融资、建设、运营维护，并在特许经营期满后无偿将项目移交给沙湾县政府指定单位。<\/p>","version":2,"begin_bid_time":null,"investment_scale":"1.3507亿元","winning_category":null,"operation_pattern_ext":null,"pre_bid_notice_end_date":null,"first_industry":[{"value":"公用事业"}],"operate_phase":"348","create_user":9,"open_bid_notice":null,"city":[{"name":"塔城地区"}],"pre_bid_notice_begin_date":null,"cooperation_phase":"30年","remark":null,"project_types":null,"audit_time":null,"collection_bid":"项目垃圾处理补贴费报价90元/吨\n项目暂定投资总额：13506.68万元","agency_company":{"update_time":"2017-04-19 00:00:00","update_user":1,"create_time":"2017-04-19 00:00:00","name":"国信招标集团股份有限公司","id":2782,"create_user":1,"version":0},"update_time":"2018-01-23 14:24:46","company_single":[],"update_user":9,"notice_url":"\"[]\"","payment_method_detail":null,"submit_audit_time":"2018-01-23 14:24:46","win_bid_time":"2018-01-22","agency":"2782","view_company_project":[{"area":"华北地区","abbreviate":"四川中资环科环保科技有限公司","is_listed":"非上市公司","create_time":"2018-01-23 14:23:05","nature":{"value":"民营企业"},"remark":null,"type":"INVESTMENT","version":1,"update_time":"2018-01-23 17:47:30","update_user":2,"province":{"name":"北京"},"parent_id":null,"name":"四川中资环科环保科技有限公司","pivot":{"company_id":6387,"project_id":21771},"id":6387,"create_user":9},{"area":"华北地区","abbreviate":"苏中建设有限责任公司","is_listed":"非上市公司","create_time":"2018-01-23 14:23:11","nature":{"value":"民营企业"},"remark":null,"type":"INVESTMENT","version":1,"update_time":"2018-01-23 17:47:45","update_user":2,"province":{"name":"北京"},"parent_id":null,"name":"苏中建设有限责任公司","pivot":{"company_id":6388,"project_id":21771},"id":6388,"create_user":9}],"serial_num":"201709210006","is_allow_union":1,"operate_phase_ext":null,"collection_bidder":"四川中资环科环保科技有限公司（牵头方）\n苏中建设有限责任公司（联合体成员二）","sys_dictionary_operation_pattern":[],"project_schedule":"BID","procurement_mode":[{"value":"公开招标"}],"second_industry":[{"value":"固废环卫"}],"investment_scale_ext":null,"prequalification_notice":"<p>沙湾县生活垃圾综合处理厂PPP项目已纳入沙湾县政府采购计划，项目拟采用PPP模式进行项目的投融资建设。沙湾县住房和城乡建设局（以下简称住建局）经沙湾县政府授权为本项目的实施机构，目前项目已具备采购条件。国信招标集团股份有限公司受沙湾县住房和城乡建设局的委托，现通过公开招标方式选择社会资本,特邀请有意向的潜在申请人（以下简称申请人）提出项目的资格预审申请。<\/p><p>一、采购项目编号：GXTC-1751112<\/p><p>二、项目名称：沙湾县生活垃圾综合处理厂PPP项目<\/p><p>三、本项目暂定总投资：人民币13506.68万元。<\/p><p>四、项目概况<\/p><p>随着生活垃圾对环境的污染和公共卫生安全的危害日益显现，为了加强生活垃圾管理，维护城市面貌和环境卫生，实现生活垃圾的无害化、减量化和资源化处置，因此沙湾县决定启动建设生活垃圾综合处理厂项目。根据项目规划要求，本项目拟处理沙湾县城与周边乡镇产生的生活垃圾。<\/p><p>沙湾县生活垃圾综合处理厂项目的设计处理总规模为300吨/日。生活垃圾综合处理厂初步拟建于沙湾县城北侧9公里处的规划红线范围内。<\/p><p>本项目拟采用热解还原综合处理技术工艺。项目的主要建设内容包括：热解还原系统、逆流烘干系统、复合烟气净化系统、燃气发电系统、污水处理系统、实时监控系统及相关配套设施。<\/p><p>五、采购需求<\/p><p>本项目通过公开招标的方式选择社会投资人，由中标的社会投资人与政府指定的出资方代表沙湾县汇福融祥投资有限公司共同在项目所在地组建项目公司，项目资本金比例为20%（即2701.34万元），其中政府方出资代表和社会资本方占项目公司股权比例分别为10%、90%（政府出资270万元，合格的社会资本自筹2431.34万元），债务性融资为80%（即10805.34万元），融资期限20年。本项目采用政府和社会资本合作（PPP）模式，具体运作方式为建设运营移交（BOT），回报机制为可行性缺口补助。项目公司获得政府授予的特许经营权，特许经营期为30年（含建设期1年，运营维护期29年）。项目公司负责项目的投融资、建设、运营维护，并在特许经营期满后无偿将项目移交给沙湾县政府指定单位。<\/p><p>六、申请人资格条件<\/p><p>1.申请人需满足《中华人民共和国政府采购法》第二十二条的相关规定：<\/p><p>1)投标人必须是在中华人民共和国境内（不含港、澳、台企业）依法注册的企业法人，具有独立承担民事责任的能力，且具有有效的营业执照、税务登记证书、组织机构代码证；申请人注册资金不低于5000万人民币（联合体投标的，至少一方满足对注册资本金的要求）；<\/p><p>2)具有良好的商业信誉和健全的财务会计制度；<\/p><p>3)有依法缴纳税收和社会保障资金的良好记录；<\/p><p>4)参加政府采购活动前三年内，在经营活动中没有重大违法的声明；<\/p><p>5)法律、行政法规规定的其他条件。<\/p><p>2.申请人须无行贿犯罪记录；<\/p><p>3.申请人应有良好的财务状况，须提供2016年度的财务报告或审计报告；<\/p><p>4.申请人至少在2016年7月1日至2017年7月1日至少具有一个合同额不低于500万元的环保工程项目业绩；<\/p><p>5.供应商在信用中国网站（www.creditchina.gov.cn）和《中国政府采购网》（www.ccgp.gov.cn）上被列入失信被执行人、重大税收违法案件当事人名单、政府采购严重违法失信行为记录名单的，不得参加投标；<\/p><p>6.本项目接受联合体申请。但联合体成员单位不超过两家，联合体各方除上述第1条、第2条和第5条均需满足外，第3条、第4条需至少有联合体成员中一方满足。<\/p><p>七、购买资格预审文件的时间及地点<\/p><p>有意向且符合上述资格条件的申请人应当在2017年9月21日起至2017年9月27日（10时00分-13时00分，14时00分-18时00分，节假日除外），到新疆乌鲁木齐市天山区人民路2号乌鲁木齐大厦9层A座报名并购买资格预审文件，资格预审文件每套售价人民币200元。<\/p><p>购买资格预审文件时须提交的资料：《单位介绍信》或《授权书》、及购买人的身份证复印件加盖申请人公章并填写购买标书登记表。<\/p><p>备注：申请人可远程邮购本项目的资格预审文件，具体购买手续请联系本项目的采购代理机构联系人。<\/p><p>网上报名领取资格预审文件：<\/p><p>（1）本项目的资格预审文件在国信创新招标投标交易平台（官方网址：http://www.e-bidding.org）在线售卖。<\/p><p>（2）潜在申请人登陆国信创新招标投标交易平台后，应认真阅读有关报名和购买资格预审文件的须知，提交报名资质，审核通过后，采用电汇方式支付（账户信息附后），请上传缴纳凭证至国信创新平台。标书款支付成功后，即可在线下载资格预审文件。潜在申请人若需要开具增值税专用发票，请随缴纳凭证上传一般纳税人证明和相关信息(单位名称、纳税人识别号、地址、电话、开户行及账号)。<\/p><p>（3）在国信创新平台上操作的一切事宜，包括注册、报名和支付标书费等，都请联系指定负责人王康华（400-0809-508）。<\/p><p>八、资格审查及确定潜在申请人的方法<\/p><p>本资格预审采用合格制，所有通过资格预审的申请人均可参与本项目后续采购。资格预审合格的申请人少于3名时，则按《政府和社会资本合作项目政府采购管理办法》（财库〔2014〕215号）第八条规定执行；<\/p><p>采购代理机构将在资格预审结束后三（3）个工作日内向资格预审合格的供应商发出书面的预审结果，未参加本次资格预审及资格预审不合格的申请人均不得参加本项目后续采购。<\/p><p>九、资格预审申请文件递交截止时间：2017年10月17日上午11时（北京时间）。<\/p><p>十、资格预审申请文件递交地点：新疆沙湾县智慧大道西路60号阿里巴巴大楼3楼招标办公室；申请人的法定代表人（需携带法定代表人身份证明文件）或者授权代表（需携带法定代表人授权书及被授权人的身份证原件）递交资格预审申请文件。<\/p><p>十一、本项目需要落实的采购政策<\/p><p>1）执行节能产品政府优先采购和强制采购制度，本项目不涉及；<\/p><p>2）执行环境标志产品政府优先采购制度；<\/p><p>3）执行《政府采购促进中小企业发展暂行办法》；<\/p><p>4）执行《政府采购进口产品管理办法》，本项目不涉及进口产品；<\/p><p>5）执行《自主创新产品政府首购和订购管理办法》。<\/p><p>十二、联系方式<\/p><p>采购机构联系人：魏志萍<\/p><p>联系电话：0993-6022267<\/p><p>联系地址：沙湾县广场西路一号<\/p><p>采购代理机构联系人：侯文权、孙守宏<\/p><p>传真：0991-2329136、0993-6096977<\/p><p>电话：18199105799、181169951770993-6096977<\/p><p>联系地址：国信招标集团股份有限公司<\/p><p>地址：北京市海淀区首体南路22号国兴大厦10层<\/p><p>邮箱：gxxj_hwq@163.com、1398989805@qq.com<\/p><p>标书款汇款账户<\/p><p>开户名称：国信招标集团股份有限公司新疆招标咨询分公司<\/p><p>开户银行：中国银行股份有限公司乌鲁木齐市人民路支行<\/p><p>帐号：107045574327（标书款专用账户）<\/p><p>注：请申请人在汇款时务必注明所投标项目的项目编号，否则，因款项用途不明导致报名无效等后果由申请人自行承担。同时，各潜在申请人在缴纳标书款后须向我方说明开具增值税发票的类型（专票或普票）并同时提供开票信息，因潜在申请人表示不明确导致发票误开的责任由潜在申请人自负，发票开具后概不退换<\/p><p>国信招标集团股份有限公司<\/p><p>2017年9月20日<\/p>","bid":[{"company_type":"UNION","create_time":"2018-01-23 14:24:46","sys_dictionary":{"id":185,"value":"元/吨"},"bid_type":{"id":132,"value":"其他"},"type":132,"version":0,"cal_value":null,"unit":185,"update_time":"2018-01-23 14:24:46","update_user":9,"project_id":21771,"second_type":null,"name":"项目垃圾处理补贴费报价","company":6616,"id":41719,"create_user":9,"value":"90"},{"company_type":"UNION","create_time":"2018-01-23 14:24:46","sys_dictionary":{"id":47,"value":"万元"},"bid_type":{"id":132,"value":"其他"},"type":132,"version":0,"cal_value":null,"unit":47,"update_time":"2018-01-23 14:24:46","update_user":9,"project_id":21771,"second_type":null,"name":"项目暂定投资总额","company":6616,"id":41720,"create_user":9,"value":"13506.68"}],"build_phase":"12","bid_company_id":[{"name":"沙湾县住房和城乡建设局"}]}]}